<?xml version="1.0" encoding="utf-8" ?>
<dwsync>
<file name="bqhns_stylesheet.css" server="205.178.145.65" local="129535097504109807" remote="129535241400000000" />
<file name="bqhns_stylesheet2.css" server="205.178.145.65" local="128417328000000000" remote="128417328000000000" />
<file name="bqhns_stylesheet_css.old" server="205.178.145.65" local="128417328000000000" remote="128417328000000000" />
<file name="menucss.css" server="205.178.145.65" local="129535102403497560" remote="129535246200000000" />
<file name="site.css" server="205.178.145.65" local="129457391028649688" remote="129457532400000000" />
<file name="sitecss.css" server="205.178.145.65" local="129480684431418264" remote="129480825000000000" />
<file name="bqhns_stylesheet.css" server="206.188.192.254/htdocs/" local="130394816890280536" remote="130394961000000000" />
<file name="menucss.css" server="206.188.192.254/htdocs/" local="130090458686887970" remote="130090602600000000" />
<file name="menu.css" server="206.188.192.254/htdocs/" local="130246336814196949" remote="130246480800000000" />
<file name="jquery-ui.css" server="206.188.192.254/htdocs/" local="130254119365170567" remote="130254264600000000" />
<file name="slides.css" server="206.188.192.254/htdocs/" local="130678020077811096" remote="130678200000000000" />
<file name="site.css" server="206.188.192.254/htdocs/" local="130708600008546647" remote="130708744200000000" />
</dwsync>